Metadata-Version: 1.1
Name: ri-pdnssdk
Version: 0.0.0a5
Summary: RI PassiveDNS SDK
Home-page: https://github.com/renisac/pdnssdk-py
Author: Wes Young
Author-email: wes@ren-isac.net
License: LGPL3
Keywords: security
Platform: UNKNOWN
Classifier: Topic :: System :: Networking
Classifier: Environment :: Other Environment
Classifier: Intended Audience :: Developers
Classifier: License :: OSI Approved :: GNU Lesser General Public License v3 (LGPLv3)
Classifier: Programming Language :: Python
